modbus_device_scanner/__init__.py
modbus_device_scanner/modbus_device_scanner.py
modbus_device_scanner-0.1.dist-info/METADATA
modbus_device_scanner-0.1.dist-info/WHEEL
modbus_device_scanner-0.1.dist-info/entry_points.txt
modbus_device_scanner-0.1.dist-info/top_level.txt
modbus_device_scanner-0.1.dist-info/RECORD
