Metadata-Version: 2.1
Name: modbus-device-scanner
Version: 0.1
Summary: A package to scan for Modbus TCP devices on a network
Home-page: https://github.com/kvjoshi/modbus_device_scanner
Author: Karmavir
Author-email: karmavirj@protonmail.com
Classifier: Programming Language :: Python :: 3
Classifier: License :: OSI Approved :: MIT License
Classifier: Operating System :: OS Independent
Requires-Python: >=3.6
Requires-Dist: ipaddress>=1.0.23
Requires-Dist: argparse>=1.4.0
